download_latest/__init__.py
download_latest/cache.py
download_latest/cls.py
download_latest/console.py
download_latest/fetch.py
download_latest/meta.py
download_latest/meter.py
download_latest/spinner.py
download_latest/task.py
download_latest/util.py
download_latest-0.2.0.dist-info/LICENSE
download_latest-0.2.0.dist-info/METADATA
download_latest-0.2.0.dist-info/WHEEL
download_latest-0.2.0.dist-info/entry_points.txt
download_latest-0.2.0.dist-info/RECORD
