Metadata-Version: 2.1
Name: download-latest
Version: 0.2.0
Summary: Download a file only if the remote file has changed.
Home-page: https://gitlab.com/jagaro/download-latest
License: GPL-3.0-or-later
Keywords: curl,download,wget
Author: Jāgaro
Author-email: jagaro@dayam.org
Requires-Python: >=3.7,<4.0
Classifier: License :: OSI Approved :: GNU General Public License v3 or later (GPLv3+)
Classifier: Programming Language :: Python :: 3
Classifier: Programming Language :: Python :: 3.7
Classifier: Programming Language :: Python :: 3.8
Classifier: Programming Language :: Python :: 3.9
Classifier: Programming Language :: Python :: 3.10
Classifier: Programming Language :: Python :: 3.11
Classifier: Programming Language :: Python :: 3.12
Requires-Dist: importlib-metadata (>=3.0.0) ; python_version < "3.8"
Project-URL: Repository, https://gitlab.com/jagaro/download-latest
